fr_word_segment/__init__.py
fr_word_segment/main.py
fr_word_segment/wordseg.py
fr_word_segment/.ipynb_checkpoints/main-checkpoint.py
fr_word_segment/__pycache__/__init__.cpython-36.pyc
fr_word_segment/__pycache__/helpers.cpython-36.pyc
fr_word_segment/__pycache__/wordseg.cpython-36.pyc
fr_word_segment-0.1.3.dist-info/LICENSE
fr_word_segment-0.1.3.dist-info/METADATA
fr_word_segment-0.1.3.dist-info/WHEEL
fr_word_segment-0.1.3.dist-info/top_level.txt
fr_word_segment-0.1.3.dist-info/RECORD
