Metadata-Version: 2.1
Name: fr-word-segment
Version: 0.1.3
Summary: A package that split mispelled words semantically
Home-page: https://github.com/PaacMaan/semantic_word_segmentation.git
Author: Ayoub RMIDI
Author-email: ayoub.rmidi@gmail.com
License: MIT
Platform: UNKNOWN
Classifier: License :: OSI Approved :: MIT License
Classifier: Programming Language :: Python :: 3
Classifier: Programming Language :: Python :: 3.6
Classifier: Programming Language :: Python :: 3.5
Requires-Python: >3.5.2
Requires-Dist: spacy
